pip_services3_postgres/__init__.py
pip_services3_postgres/build/DefaultPostgresFactory.py
pip_services3_postgres/build/__init__.py
pip_services3_postgres/connect/PostgresConnection.py
pip_services3_postgres/connect/PostgresConnectionResolver.py
pip_services3_postgres/connect/__init__.py
pip_services3_postgres/persistence/IdentifiableJsonPostgresPersistence.py
pip_services3_postgres/persistence/IdentifiablePostgresPersistence.py
pip_services3_postgres/persistence/PostgresPersistence.py
pip_services3_postgres/persistence/__init__.py
pip_services3_postgres-3.2.8.dist-info/METADATA
pip_services3_postgres-3.2.8.dist-info/WHEEL
pip_services3_postgres-3.2.8.dist-info/top_level.txt
pip_services3_postgres-3.2.8.dist-info/zip-safe
pip_services3_postgres-3.2.8.dist-info/RECORD
